LICENSE
README.rst
setup.cfg
setup.py
hydedown/__init__.py
hydedown/passthrough.py
hydedown/sections.py
hydedown.egg-info/PKG-INFO
hydedown.egg-info/SOURCES.txt
hydedown.egg-info/dependency_links.txt
hydedown.egg-info/requires.txt
hydedown.egg-info/top_level.txt
hydedown/tests/__init__.py
hydedown/tests/test_extensions.py