Metadata-Version: 1.1
Name: hydedown
Version: 0.1.2
Summary: Markdown extensions that facilitate hyde website generation
Home-page: http://github.com/hyde/hydedown
Author: Hyde contributors
Author-email: hyde-dev@googlegroups.com
License: MIT
Platform: UNKNOWN
Classifier: Development Status :: 3 - Alpha
Classifier: Intended Audience :: Developers
Classifier: License :: OSI Approved :: MIT License
Classifier: Operating System :: OS Independent
Classifier: Programming Language :: Python
Classifier: Topic :: Software Development
